pysixtrack/__init__.py
pysixtrack/base_classes.py
pysixtrack/closed_orbit.py
pysixtrack/elements.py
pysixtrack/line.py
pysixtrack/linear_normal_form.py
pysixtrack/loader_mad.py
pysixtrack/loader_sixtrack.py
pysixtrack/mathlibs.py
pysixtrack/particles.py
pysixtrack/be_beamfields/BB6D.py
pysixtrack/be_beamfields/BB6Ddata.py
pysixtrack/be_beamfields/__init__.py
pysixtrack/be_beamfields/beambeam.py
pysixtrack/be_beamfields/boost.py
pysixtrack/be_beamfields/gaussian_fields.py
pysixtrack/be_beamfields/propagate_sigma_matrix.py
pysixtrack/be_beamfields/qgauss.py
pysixtrack/be_beamfields/slicing.py
pysixtrack/be_beamfields/spacecharge.py
pysixtrack/be_beamfields/tools.py
pysixtrack-0.0.6.dist-info/LICENSE
pysixtrack-0.0.6.dist-info/METADATA
pysixtrack-0.0.6.dist-info/WHEEL
pysixtrack-0.0.6.dist-info/top_level.txt
pysixtrack-0.0.6.dist-info/RECORD
