Metadata-Version: 2.1
Name: pysixtrack
Version: 0.0.6
Summary: 6D Tracking Code
Home-page: https://github.com/rdemaria/pysixtrack
Author: Riccardo De Maria
Author-email: riccardo.de.maria@cern.ch
License: UNKNOWN
Platform: UNKNOWN
Requires-Dist: numpy
